LICENSE
README.md
setup.py
pgrestpy/__init__.py
pgrestpy/client.py
pgrestpy/server.py
pgrestpy.egg-info/PKG-INFO
pgrestpy.egg-info/SOURCES.txt
pgrestpy.egg-info/dependency_links.txt
pgrestpy.egg-info/requires.txt
pgrestpy.egg-info/top_level.txt