Metadata-Version: 2.1
Name: pgrestpy
Version: 0.0.7
Summary: Simple REST client for PostgreSQL-compatible databases
Home-page: https://github.com/xdgrulez/pgrest.py
Author: Ralph M. Debusmann
Author-email: matthias.debusmann@gmail.com
License: Apache License 2.0
Platform: UNKNOWN
Classifier: Development Status :: 3 - Alpha
Classifier: Intended Audience :: Developers
Classifier: License :: OSI Approved :: Apache Software License
Classifier: Programming Language :: Python :: 3.10
Classifier: Topic :: Software Development :: Libraries :: Python Modules
License-File: LICENSE
